demo/__init__.py
demo/demo_ip.py
demo/demo_url.py
supply_chain_demo-0.1.2.dist-info/METADATA
supply_chain_demo-0.1.2.dist-info/WHEEL
supply_chain_demo-0.1.2.dist-info/top_level.txt
supply_chain_demo-0.1.2.dist-info/RECORD
