Metadata-Version: 2.1
Name: supply-chain-demo
Version: 0.1.2
Summary: Supply Chain Demo
Author: Demo
License: Apache License, Version 2.0
Requires-Python: >=3.7
Requires-Dist: requests
